skylink/__init__.py
skylink/class1.py
skylink/skylink.py
skylink-0.2.dist-info/License.txt
skylink-0.2.dist-info/METADATA
skylink-0.2.dist-info/WHEEL
skylink-0.2.dist-info/top_level.txt
skylink-0.2.dist-info/RECORD
