Metadata-Version: 2.1
Name: skylink
Version: 0.2
Summary: Chatbot link v2
Author: Caique santos carvalho
License-File: License.txt
